INSTALL.rst
MANIFEST.in
NEWS.rst
setup.cfg
setup.py
scripts/pycoco
src/pycoco/__init__.py
src/pycoco/coverage.css
src/pycoco/coverage.js
src/pycoco/coverage_sortfilelist.css
src/pycoco/xmlns.py
src/pycoco.egg-info/PKG-INFO
src/pycoco.egg-info/SOURCES.txt
src/pycoco.egg-info/dependency_links.txt
src/pycoco.egg-info/entry_points.txt
src/pycoco.egg-info/not-zip-safe
src/pycoco.egg-info/requires.txt
src/pycoco.egg-info/top_level.txt