Metadata-Version: 1.0
Name: pycoco
Version: 0.7.1
Summary: Python code coverage
Home-page: http://www.livinglogic.de/Python/pycoco/
Author: Walter Doerwald
Author-email: walter@livinglogic.de
License: Python
Download-URL: http://www.livinglogic.de/Python/Download.html#pycoco
Keywords: Python,code coverage,coverage,source code,subversion,test
Platform: UNKNOWN
Classifier: Development Status :: 4 - Beta
Classifier: Intended Audience :: Developers
Classifier: License :: OSI Approved :: Python License (CNRI Python License)
Classifier: Operating System :: OS Independent
Classifier: Programming Language :: Python
Classifier: Topic :: Software Development :: Testing
